Makefile
binary_tree_dict_mod.m4
binary_tree_dict_mod.py
setup.py
test-binary_tree_dict_mod
this-pylint
binary_tree_dict_mod.egg-info/PKG-INFO
binary_tree_dict_mod.egg-info/SOURCES.txt
binary_tree_dict_mod.egg-info/dependency_links.txt
binary_tree_dict_mod.egg-info/top_level.txt