Metadata-Version: 1.1
Name: binary-tree-dict-mod
Version: 1.0
Summary: Pure Python binary tree (dictionary) module
Home-page: http://stromberg.dnsalias.org/~strombrg/binary-tree-dict/
Author: Daniel Richard Stromberg
Author-email: strombrg@gmail.com
License: Apache v2
Keywords: binary tree,dictionary-like,sorted dictionary,cache
Platform: Cross platform
Classifier: Development Status :: 5 - Production/Stable
Classifier: Intended Audience :: Developers
Classifier: Programming Language :: Python :: 2
Classifier: Programming Language :: Python :: 3
